{
  "norad_id": 53746,
  "name": "STARLINK-4589",
  "history": [
    {
      "epoch": "2026-03-28T18:33:04.966560Z",
      "apogee_km": 540.5640670798293,
      "perigee_km": 538.9224540939913,
      "latitude_deg": 4.09377042102462e-06,
      "longitude_deg": 74.04349507927537,
      "height_km": 540.6055494121168,
      "semi_major_axis_km": 6917.88026058691,
      "eccentricity": 0.00011865,
      "inclination_deg": 53.2156,
      "raan_deg": 178.5028,
      "arg_perigee_deg": 87.6633,
      "mean_anomaly_deg": 272.4495,
      "mean_motion_rev_day": 15.08840042
    },
    {
      "epoch": "2026-03-29T05:40:48.084096Z",
      "apogee_km": 540.4741503522428,
      "perigee_km": 539.098867158702,
      "latitude_deg": -8.505975576190757e-07,
      "longitude_deg": -95.42490212453028,
      "height_km": 540.67955462304,
      "semi_major_axis_km": 6917.923508755472,
      "eccentricity": 9.94e-05,
      "inclination_deg": 53.2161,
      "raan_deg": 176.4211,
      "arg_perigee_deg": 89.7488,
      "mean_anomaly_deg": 270.3618,
      "mean_motion_rev_day": 15.08825893
    },
    {
      "epoch": "2026-03-29T23:10:01.666848Z",
      "apogee_km": 540.6386511452465,
      "perigee_km": 538.8206357913441,
      "latitude_deg": -6.457902590980312e-06,
      "longitude_deg": -1.721170661116829,
      "height_km": 540.428806262688,
      "semi_major_axis_km": 6917.8666434682955,
      "eccentricity": 0.0001314,
      "inclination_deg": 53.2163,
      "raan_deg": 173.1496,
      "arg_perigee_deg": 77.5133,
      "mean_anomaly_deg": 282.6006,
      "mean_motion_rev_day": 15.08844497
    },
    {
      "epoch": "2026-03-30T05:31:34.527936Z",
      "apogee_km": 540.5468402054803,
      "perigee_km": 538.9241840290388,
      "latitude_deg": -1.7038719535315616e-05,
      "longitude_deg": -98.5580595555308,
      "height_km": 540.579516189002,
      "semi_major_axis_km": 6917.872512117259,
      "eccentricity": 0.00011728,
      "inclination_deg": 53.2153,
      "raan_deg": 171.9608,
      "arg_perigee_deg": 86.3434,
      "mean_anomaly_deg": 273.7692,
      "mean_motion_rev_day": 15.08842577
    },
    {
      "epoch": "2026-03-30T11:53:06.940608Z",
      "apogee_km": 540.5491507965999,
      "perigee_km": 538.8718494917157,
      "latitude_deg": -1.8504629931431512e-05,
      "longitude_deg": 164.6065318657384,
      "height_km": 540.5178153754687,
      "semi_major_axis_km": 6917.8475001441575,
      "eccentricity": 0.00012123,
      "inclination_deg": 53.2151,
      "raan_deg": 170.7716,
      "arg_perigee_deg": 83.9516,
      "mean_anomaly_deg": 276.1614,
      "mean_motion_rev_day": 15.0885076
    },
    {
      "epoch": "2026-03-31T11:43:53.616000Z",
      "apogee_km": 540.5844657309553,
      "perigee_km": 538.8269186165817,
      "latitude_deg": 2.654882063069829e-05,
      "longitude_deg": 161.47225314686165,
      "height_km": 540.4995905203268,
      "semi_major_axis_km": 6917.842692173768,
      "eccentricity": 0.00012703,
      "inclination_deg": 53.2153,
      "raan_deg": 166.3111,
      "arg_perigee_deg": 83.3528,
      "mean_anomaly_deg": 276.7609,
      "mean_motion_rev_day": 15.08852333
    },
    {
      "epoch": "2026-04-01T11:34:40.954944Z",
      "apogee_km": 540.5898128428389,
      "perigee_km": 538.8880153679684,
      "latitude_deg": 6.6698048952309915e-06,
      "longitude_deg": 158.3351538185179,
      "height_km": 540.59761655868,
      "semi_major_axis_km": 6917.875914105403,
      "eccentricity": 0.000123,
      "inclination_deg": 53.2159,
      "raan_deg": 161.8506,
      "arg_perigee_deg": 87.5061,
      "mean_anomaly_deg": 272.6072,
      "mean_motion_rev_day": 15.08841464
    },
    {
      "epoch": "2026-04-02T13:00:50.615136Z",
      "apogee_km": 540.5960921121405,
      "perigee_km": 538.8633048615029,
      "latitude_deg": 3.320842168500729e-05,
      "longitude_deg": 130.99340368023326,
      "height_km": 540.6490091828484,
      "semi_major_axis_km": 6917.866698486821,
      "eccentricity": 0.00012524,
      "inclination_deg": 53.2164,
      "raan_deg": 157.0937,
      "arg_perigee_deg": 91.5586,
      "mean_anomaly_deg": 268.555,
      "mean_motion_rev_day": 15.08844479
    },
    {
      "epoch": "2026-04-02T20:57:46.594080Z",
      "apogee_km": 540.6190670533006,
      "perigee_km": 538.8696732124208,
      "latitude_deg": 4.787776618803945e-05,
      "longitude_deg": 9.946020191995919,
      "height_km": 540.5616405378548,
      "semi_major_axis_km": 6917.88137013286,
      "eccentricity": 0.00012644,
      "inclination_deg": 53.2166,
      "raan_deg": 155.606,
      "arg_perigee_deg": 84.8521,
      "mean_anomaly_deg": 275.2616,
      "mean_motion_rev_day": 15.08839679
    },
    {
      "epoch": "2026-04-03T14:27:00.927648Z",
      "apogee_km": 540.6374944564132,
      "perigee_km": 538.8305465458579,
      "latitude_deg": 2.013074219534271e-05,
      "longitude_deg": 103.64749790146253,
      "height_km": 540.6149674075218,
      "semi_major_axis_km": 6917.871020501135,
      "eccentricity": 0.0001306,
      "inclination_deg": 53.2162,
      "raan_deg": 152.3354,
      "arg_perigee_deg": 89.0674,
      "mean_anomaly_deg": 271.0468,
      "mean_motion_rev_day": 15.08843065
    },
    {
      "epoch": "2026-04-04T12:42:25.925472Z",
      "apogee_km": 540.7408299533163,
      "perigee_km": 538.7862463352685,
      "latitude_deg": -3.91771866016123e-05,
      "longitude_deg": 124.71533546577761,
      "height_km": 540.7380055922738,
      "semi_major_axis_km": 6917.900538144292,
      "eccentricity": 0.00014127,
      "inclination_deg": 53.2161,
      "raan_deg": 148.1715,
      "arg_perigee_deg": 94.6345,
      "mean_anomaly_deg": 265.4808,
      "mean_motion_rev_day": 15.08833408
    },
    {
      "epoch": "2026-04-05T09:22:26.648544Z",
      "apogee_km": 540.6638955296303,
      "perigee_km": 538.8566640442596,
      "latitude_deg": 4.603137348409524e-05,
      "longitude_deg": 169.99652678712124,
      "height_km": 540.7197140417381,
      "semi_major_axis_km": 6917.897279786945,
      "eccentricity": 0.00013062,
      "inclination_deg": 53.2157,
      "raan_deg": 144.3044,
      "arg_perigee_deg": 94.0513,
      "mean_anomaly_deg": 266.0629,
      "mean_motion_rev_day": 15.08834474
    },
    {
      "epoch": "2026-04-06T02:51:41.159232Z",
      "apogee_km": 540.6597104883349,
      "perigee_km": 538.8636856283447,
      "latitude_deg": 2.2259495825689725e-05,
      "longitude_deg": -96.30133399983731,
      "height_km": 540.6978436958514,
      "semi_major_axis_km": 6917.8986980583395,
      "eccentricity": 0.00012981,
      "inclination_deg": 53.2162,
      "raan_deg": 141.0352,
      "arg_perigee_deg": 92.584,
      "mean_anomaly_deg": 267.5301,
      "mean_motion_rev_day": 15.0883401
    },
    {
      "epoch": "2026-04-07T12:14:46.344768Z",
      "apogee_km": 540.5870161680441,
      "perigee_km": 538.8632232850514,
      "latitude_deg": 9.431863262835563e-06,
      "longitude_deg": 115.31118244086252,
      "height_km": 540.6286771495888,
      "semi_major_axis_km": 6917.8621197265475,
      "eccentricity": 0.00012459,
      "inclination_deg": 53.2161,
      "raan_deg": 134.7904,
      "arg_perigee_deg": 90.5206,
      "mean_anomaly_deg": 269.5929,
      "mean_motion_rev_day": 15.08845977
    },
    {
      "epoch": "2026-04-08T12:05:34.149408Z",
      "apogee_km": 540.6238043581943,
      "perigee_km": 538.8806346326664,
      "latitude_deg": 4.708394125988303e-05,
      "longitude_deg": 112.1711758735294,
      "height_km": 540.67697051853,
      "semi_major_axis_km": 6917.889219495431,
      "eccentricity": 0.00012599,
      "inclination_deg": 53.2162,
      "raan_deg": 130.3289,
      "arg_perigee_deg": 91.9095,
      "mean_anomaly_deg": 268.2042,
      "mean_motion_rev_day": 15.08837111
    },
    {
      "epoch": "2026-04-09T08:45:34.230528Z",
      "apogee_km": 540.6320769227332,
      "perigee_km": 538.8194585203346,
      "latitude_deg": -1.59738489794967e-05,
      "longitude_deg": 157.45693762636577,
      "height_km": 540.6434172335622,
      "semi_major_axis_km": 6917.862767721534,
      "eccentricity": 0.00013101,
      "inclination_deg": 53.2156,
      "raan_deg": 126.4638,
      "arg_perigee_deg": 91.3948,
      "mean_anomaly_deg": 268.7194,
      "mean_motion_rev_day": 15.08845765
    },
    {
      "epoch": "2026-04-10T00:39:25.854048Z",
      "apogee_km": 540.6557301283556,
      "perigee_km": 538.8384019842033,
      "latitude_deg": -6.551850665581406e-06,
      "longitude_deg": -84.63334951905519,
      "height_km": 540.7201060607111,
      "semi_major_axis_km": 6917.884066056279,
      "eccentricity": 0.00013135,
      "inclination_deg": 53.2146,
      "raan_deg": 123.4915,
      "arg_perigee_deg": 94.8966,
      "mean_anomaly_deg": 265.2176,
      "mean_motion_rev_day": 15.08838797
    },
    {
      "epoch": "2026-04-11T10:02:32.700192Z",
      "apogee_km": 540.6364579688989,
      "perigee_km": 538.8903799031605,
      "latitude_deg": -3.268040968390516e-05,
      "longitude_deg": 126.97081959715946,
      "height_km": 540.6032200990953,
      "semi_major_axis_km": 6917.900418936029,
      "eccentricity": 0.0001262,
      "inclination_deg": 53.2153,
      "raan_deg": 117.2453,
      "arg_perigee_deg": 86.3339,
      "mean_anomaly_deg": 273.7797,
      "mean_motion_rev_day": 15.08833447
    },
    {
      "epoch": "2026-04-12T17:50:15.561888Z",
      "apogee_km": 540.654951518809,
      "perigee_km": 538.8698567565652,
      "latitude_deg": -2.588061965359151e-05,
      "longitude_deg": 2.7887488879910616,
      "height_km": 540.5769265180777,
      "semi_major_axis_km": 6917.899404137687,
      "eccentricity": 0.00012902,
      "inclination_deg": 53.2158,
      "raan_deg": 111.2976,
      "arg_perigee_deg": 84.7854,
      "mean_anomaly_deg": 275.3285,
      "mean_motion_rev_day": 15.08833779
    },
    {
      "epoch": "2026-04-14T17:31:49.724832Z",
      "apogee_km": 540.6185595763045,
      "perigee_km": 538.8766362345514,
      "latitude_deg": -2.7540435763988703e-05,
      "longitude_deg": -3.4848710275342003,
      "height_km": 540.6167412305425,
      "semi_major_axis_km": 6917.884597905428,
      "eccentricity": 0.0001259,
      "inclination_deg": 53.2186,
      "raan_deg": 102.375,
      "arg_perigee_deg": 88.2344,
      "mean_anomaly_deg": 271.8792,
      "mean_motion_rev_day": 15.08838623
    },
    {
      "epoch": "2026-04-15T11:01:04.013472Z",
      "apogee_km": 540.6164947936768,
      "perigee_km": 538.857971163653,
      "latitude_deg": 8.023360705881712e-06,
      "longitude_deg": 90.21774274980021,
      "height_km": 540.4941431199063,
      "semi_major_axis_km": 6917.874232978665,
      "eccentricity": 0.0001271,
      "inclination_deg": 53.2162,
      "raan_deg": 99.1053,
      "arg_perigee_deg": 80.9163,
      "mean_anomaly_deg": 279.1973,
      "mean_motion_rev_day": 15.08842014
    },
    {
      "epoch": "2026-04-16T15:38:00.254976Z",
      "apogee_km": 540.5376530391577,
      "perigee_km": 538.9313232796067,
      "latitude_deg": -3.7645408270218735e-05,
      "longitude_deg": 14.453969644744525,
      "height_km": 540.4436399122545,
      "semi_major_axis_km": 6917.871488159381,
      "eccentricity": 0.0001161,
      "inclination_deg": 53.2166,
      "raan_deg": 93.7511,
      "arg_perigee_deg": 76.5513,
      "mean_anomaly_deg": 283.5608,
      "mean_motion_rev_day": 15.08842912
    },
    {
      "epoch": "2026-04-17T21:50:20.192352Z",
      "apogee_km": 540.6763076135285,
      "perigee_km": 538.8213457079664,
      "latitude_deg": -3.334018281727358e-05,
      "longitude_deg": -85.5176952157842,
      "height_km": 540.4849957095549,
      "semi_major_axis_km": 6917.885826660747,
      "eccentricity": 0.00013407,
      "inclination_deg": 53.2157,
      "raan_deg": 88.103,
      "arg_perigee_deg": 80.1027,
      "mean_anomaly_deg": 280.0116,
      "mean_motion_rev_day": 15.08838221
    },
    {
      "epoch": "2026-04-18T15:19:34.609728Z",
      "apogee_km": 540.6835677476147,
      "perigee_km": 538.8046712355599,
      "latitude_deg": -5.864293535935427e-05,
      "longitude_deg": 8.182634210958184,
      "height_km": 540.4908804892292,
      "semi_major_axis_km": 6917.881119491587,
      "eccentricity": 0.0001358,
      "inclination_deg": 53.2163,
      "raan_deg": 84.8316,
      "arg_perigee_deg": 80.8824,
      "mean_anomaly_deg": 279.2321,
      "mean_motion_rev_day": 15.08839761
    },
    {
      "epoch": "2026-04-19T15:10:21.767232Z",
      "apogee_km": 540.6852825329806,
      "perigee_km": 538.8160692829497,
      "latitude_deg": -3.515146940740567e-05,
      "longitude_deg": 5.046323091066081,
      "height_km": 540.5181132817507,
      "semi_major_axis_km": 6917.887675907965,
      "eccentricity": 0.0001351,
      "inclination_deg": 53.2166,
      "raan_deg": 80.3711,
      "arg_perigee_deg": 82.1146,
      "mean_anomaly_deg": 277.9999,
      "mean_motion_rev_day": 15.08837616
    },
    {
      "epoch": "2026-04-20T03:53:27.066912Z",
      "apogee_km": 540.6972784423169,
      "perigee_km": 538.8034375991865,
      "latitude_deg": 3.539800494742552e-05,
      "longitude_deg": 171.3731773251577,
      "height_km": 540.520371769564,
      "semi_major_axis_km": 6917.887358020752,
      "eccentricity": 0.00013688,
      "inclination_deg": 53.2172,
      "raan_deg": 77.9923,
      "arg_perigee_deg": 82.3734,
      "mean_anomaly_deg": 277.7414,
      "mean_motion_rev_day": 15.0883772
    },
    {
      "epoch": "2026-04-21T21:13:28.169184Z",
      "apogee_km": 540.6825676129083,
      "perigee_km": 538.8700743228137,
      "latitude_deg": -1.8939098401009972e-05,
      "longitude_deg": -98.06247230108984,
      "height_km": 540.6776769195648,
      "semi_major_axis_km": 6917.91332096786,
      "eccentricity": 0.000131,
      "inclination_deg": 53.217,
      "raan_deg": 70.2588,
      "arg_perigee_deg": 90.3556,
      "mean_anomaly_deg": 269.7586,
      "mean_motion_rev_day": 15.08829226
    },
    {
      "epoch": "2026-04-22T06:45:46.469376Z",
      "apogee_km": 540.2833098234869,
      "perigee_km": 538.9746068594877,
      "latitude_deg": 4.573542469241237e-05,
      "longitude_deg": 116.6862951435136,
      "height_km": 540.6817213009427,
      "semi_major_axis_km": 6917.765958341487,
      "eccentricity": 9.459e-05,
      "inclination_deg": 53.2172,
      "raan_deg": 68.4755,
      "arg_perigee_deg": 103.8351,
      "mean_anomaly_deg": 256.2747,
      "mean_motion_rev_day": 15.08877438
    },
    {
      "epoch": "2026-04-23T06:36:34.196256Z",
      "apogee_km": 540.7505238324466,
      "perigee_km": 538.8291388343114,
      "latitude_deg": -1.0081676335099214e-05,
      "longitude_deg": 113.54774472286256,
      "height_km": 540.6484350129695,
      "semi_major_axis_km": 6917.926831333379,
      "eccentricity": 0.00013887,
      "inclination_deg": 53.217,
      "raan_deg": 64.0152,
      "arg_perigee_deg": 87.7917,
      "mean_anomaly_deg": 272.3234,
      "mean_motion_rev_day": 15.08824806
    }
  ]
}